pulse_scrapy_selenium_grid/__init__.py
pulse_scrapy_selenium_grid/download_handler.py
pulse_scrapy_selenium_grid/web_driver/__init__.py
pulse_scrapy_selenium_grid/web_driver/alert.py
pulse_scrapy_selenium_grid/web_driver/proxy/__init__.py
pulse_scrapy_selenium_grid/web_driver/proxy/items.py
pulse_scrapy_selenium_grid/web_driver/proxy/proxy_extension.py
pulse_scrapy_selenium_grid/web_driver/proxy/resources/background.js
pulse_scrapy_selenium_grid/web_driver/proxy/resources/manifest.json
pulse_scrapy_selenium_grid/web_driver/remote_connection/__init__.py
pulse_scrapy_selenium_grid/web_driver/remote_connection/base.py
pulse_scrapy_selenium_grid/web_driver/remote_connection/chrome.py
pulse_scrapy_selenium_grid/web_driver/shadowroot.py
pulse_scrapy_selenium_grid/web_driver/switch_to.py
pulse_scrapy_selenium_grid/web_driver/webdriver.py
pulse_scrapy_selenium_grid/web_driver/webelement.py
pulse_scrapy_selenium_grid-0.5.7.dist-info/METADATA
pulse_scrapy_selenium_grid-0.5.7.dist-info/WHEEL
pulse_scrapy_selenium_grid-0.5.7.dist-info/RECORD
