Metadata-Version: 2.3
Name: pulse-scrapy-selenium-grid
Version: 0.5.7
Summary: Scrapy + Selenium Grid integration.
Author: Vlad Tiazhov
Author-email: vlad.tiazhov@pulseintelligence.com
Requires-Python: >=3.12
Classifier: Programming Language :: Python :: 3.13
Classifier: Operating System :: OS Independent
Requires-Dist: Scrapy (>=2.12.0)
Requires-Dist: aiohttp (>=3.11.11)
Requires-Dist: aiohttp_socks (>=0.10.1)
Requires-Dist: selenium (>=4.27.1)
Project-URL: Repository, https://github.com/Pulse-Intelligence-Partners/pulse-scrapy-selenium-grid/
